{
  "contactMedium.postCodePlaceholder": "لطفا کد پستی خود را وارد نمایید",
  "contactMedium.status": "وضعیت",
  "contactMedium.verify": "تایید",
  "contactMedium.action": "عملیات",
  "contactMedium.add": "افزودن",
  "contactMedium.done": "ثبت",
  "contactMedium.back": "قبلی",
  "contactMedium.next": "ادامه",
  "contactMedium.mediumType": "نوع",
  "contactMedium.characteristic": "مشخصات",
  "contactMedium.emailVerification": "تایید ایمیل",
  "contactMedium.mobileVerification": "تایید موبایل",
  "contactMedium.pleaseCheckYourEmail": "لطفا ایمیل خود را چک کرده و کد 6 رقمی ارسال شده را وارد نمایید",
  "contactMedium.pleaseCheckYourMobile": "لطفا تلفن خود را چک کرده و کد 6 رقمی ارسال شده را وارد نمایید",
  "contactMedium.EMAIL_ADDRESS": "ایمیل",
  "contactMedium.pleaseEnterValidEmail": "لطفا ایمیل خود را وارد نمایید",
  "contactMedium.emailPlaceholder": "لطفا ایمیل خود را وارد نمایید...",
  "contactMedium.phoneNumberPlaceHolder": " لطفا شماره تماس خود را وارد نمایید ...",
  "contactMedium.iran": "ایران",
  "contactMedium.city": "شهر",
  "contactMedium.titlePlaceHolder": " لطفا عنوان خود را وارد نمایید ...",
  "contactMedium.stateOrProvince": "استان یا شهرستان",
  "contactMedium.postalCode": "کد پستی",
  "contactMedium.postalCodePlaceHoder": "لطفا کد پستی را وارد نمایید ...",
  "contactMedium.addressLine1": "آدرس لاین 1",
  "contactMedium.addressLine2": "آدرس لاین 2",
  "contactMedium.contactMediumType": "نوع",
  "contactMedium.startDateTime": "تاریخ فعال‌سازی",
  "contactMedium.endDateTime": "پایان اعتبار",
  "contactMedium.pleaseEnterPhoneNumber": "لطفا شماره تماس خود را وارد نمایید",
  "contactMedium.country": "کشور",
  "contactMedium.contactMediumSuccessfullyVerified": "راه ارتباطی با موفقیت تایید شد",
  "contactMedium.verified": "تایید شده",
  "contactMedium.confirmed": "تایید شده",
  "contactMedium.pending": "تایید نشده",
  "contactMedium.contactType": "نوع",
  "contactMedium.sureToDelete": "از حذف این مورد اطمینان دارید؟",
  "contactMedium.yes": "بله",
  "contactMedium.no": "خیر",
  "contactMedium.email": "ایمیل",
  "contactMedium.phoneNumber": "شماره موبایل",
  "contactMedium.tellNumber": "شماره ثابت",
  "contactMedium.postalAddress": "آدرس",
  "contactMedium.iraq": "عراق",
  "contactMedium.afghanistan": "افغانستان",
  "contactMedium.pakistan": "پاکستان",
  "contactMedium.china": "چین",
  "contactMedium.turkey": "ترکیه",
  "contactMedium.unitedArabEmirates": "امارات متحده عربی"
}
